[
  {
    "key": ["url_catalog"],
    "type": "convert",
    "convert": {
      "type": "constValue",
      "params": {
        "const_value": {
          "type": "properties",
          "properties": "url.static"
        }
      }
    }
  },
  {
    "key": ["url_catalog"],
    "type": "convert",
    "convert": {
      "type": "afterAdd",
      "params": {
        "value": {
          "type": "value",
          "value": "\\html-parsing\\"
        }
      }
    }
  },
  {
    "key": ["html_text"],
    "type": "parsing_html",
    "parsingSite": {
      "type": "connectSiteHtml",
      "params": {
        "url": {
          "type": "value",
          "value": "https://xn--80aed5aobb1a.xn--p1ai/"
        }
      }
    }
  },
  {
    "key": ["file_save"],
    "type": "file",
    "file":  {
      "catalog": {
        "type": "dataset",
        "key": ["url_catalog"]
      },
      "name": {
        "type": "value",
        "value": "автолого.html"
      },
      "operation": [
        {
          "type": "createFile"
        },
        {
          "type": "outputString",
          "params": {
            "string": {
              "type": "dataset",
              "key": ["html_text"]
            }
          }
        }
      ]
    }
  }
]